gradle.properties
hexdoc_hextrogen/__gradle_version__.py
hexdoc_hextrogen/__init__.py
hexdoc_hextrogen/__version__.py
hexdoc_hextrogen/_hooks.py
hexdoc_hextrogen/py.typed
hexdoc_hextrogen/_export/.gitignore
hexdoc_hextrogen/_export/__init__.py
hexdoc_hextrogen/_export/generated/__init__.py
hexdoc_hextrogen/_export/generated/hextrogen.hexdoc.json
hexdoc_hextrogen/_export/generated/hextrogen.patterns.hexdoc.json
hexdoc_hextrogen/_export/generated/assets/estrogen/textures/mob_effect/estrogen.png
hexdoc_hextrogen/_export/generated/assets/hexcasting/lang/en_us.flatten.json5
hexdoc_hextrogen/_export/generated/assets/hexcasting/patchouli_books/thehexbook/en_us/entries/estrogen.json
hexdoc_hextrogen/_export/generated/assets/hextrogen/lang/en_us.json
hexdoc_hextrogen/_export/generated/assets/hextrogen/lang/zh_cn.json
hexdoc_hextrogen/_templates/__init__.py
hexdoc_hextrogen/_templates/index.css.jinja
hexdoc_hextrogen-1.1.0.1.0.0.dist-info/METADATA
hexdoc_hextrogen-1.1.0.1.0.0.dist-info/WHEEL
hexdoc_hextrogen-1.1.0.1.0.0.dist-info/entry_points.txt
hexdoc_hextrogen-1.1.0.1.0.0.dist-info/licenses/LICENSE
hexdoc_hextrogen-1.1.0.1.0.0.dist-info/RECORD
